{"source":{"id":"spurgeon_sermons","name":"Spurgeon's Sermons","worlddicCode":"Spurgeon_Ser"},"book":"job","chapter":36,"entries":[{"ref":"Job 36:5","book":"job","chapter":36,"sourceUrl":"https://worlddic.com/xe/view_file.php?folder=sermon31&file=Spurgeon_Ser_none_overlooked.html","title":"None Overlooked","text":"<p>None Overlooked</p><p>Spurgeon, Charles Haddon</p><p>Job 36:5</p><p>Behold, God is mighty, and despises not any: he is mighty in strength and wisdom.</p><p>&nbsp;</p><p>You can buy complete sets of all the flowers of the Alpine district at the hotel near the foot of the Rosenlaui glacier, very neatly pressed and enclosed in cases. Some of the flowers are very common, but they must be included, or the fauna would not be completely represented. The botanist is as careful to see that the common ones are there, as he is to note that the rarer specimens are not excluded. Our blessed Lord will be sure to make a perfect collection of all the flowers of His field, and even the ordinary believer, the everyday worker, the common convert, will not be forgotten. To Jesus&#39; eye, there is beauty in all His plants, and each one is needed to perfect the fauna of paradise. May I be found among His flowers, if only as one Out of myriad daisies, who with sweet simplicity shall look up and wonder at His love forever.</p><p>&nbsp;</p><p>worlddic.com</p><p>&nbsp;</p><p>&nbsp;</p>"}]}
