{"source":{"id":"ew_bullinger_companion","name":"E.W. Bullinger's Companion","worlddicCode":"Bullinger"},"book":"psalms","chapter":41,"entries":[{"ref":"Psalms 41","book":"psalms","chapter":41,"sourceUrl":"https://worlddic.com/xe/sermon4/Bullinger_psalms_41.html","text":"<p>Verse 1 </p><p>To the chief Musician. See App-64. </p><p>Title. A Psalm = Mizmor. See App-65. </p><p>of David = by David, and relating to the true David. </p><p>Blessed. See App-63. </p><p>the poor = weak, or feeble. Hebrew. dal. Not the same as Psalms 40:17. </p><p>will deliver = may the LORD deliver . . . preserve. </p><p>in time of trouble = in the evil day. </p><p>Verse 2 </p><p>keep him alive = revive, so as to live again; hence, to give life to: here, in resurrection. Hebrew. Piel conjugation, to give life, quicken. Compare Psalms 119:25, Psalms 119:37, &amp;c. Deuteronomy 32:39. Job 33:4. Hence, to preserve seed (Genesis 19:32, Genesis 19:34); to repair, in the sense of restoring what was lost (1 Chronicles 11:8, Nehemiah 4:2. Hosea 6:2; Hosea 14:7. Hosea 85:6). </p><p>will = soul. Hebrew. nephesh. </p><p>Verse 3 </p><p>the bed = the couch. </p><p>Verse 4 </p><p>be merciful = be gracious, or show favour. </p><p>my soul = me. </p><p>I have sinned. Christ could say this of those whose sins He was bearing, which were laid upon Him. sinned. Hebrew. chata. App-44. </p><p>Verse 6 </p><p>he come: i.e. the traitor; then Ahithophel, afterward Judas (see Psalms 41:9). </p><p>speaketh. Note the lying lips, the evil heart, the wicked slander. </p><p>Verse 8 </p><p>An evil disease = a thing of Belial. Compare Psalms 101:3. Deuteronomy 13:13; Deuteronomy 15:9. Judges 19:22. 1 Samuel 2:12. See 2 Samuel 16:7. </p><p>Verse 9 </p><p>mine own familiar friend: i.e. the one whom I was in the habit of saluting as my friend. </p><p>whom I trusted. These words not quoted by Christ (John 13:18), for He knew what was in man (John 2:24, John 2:25). </p><p>trusted = confided. Hebrew. batah. App-69. </p><p>which did eat, &amp;c. Quoted in John 13:18. </p><p>bread. Put by Figure of speech Synecdoche (of Species), App-6. for all kinds&quot; of food. </p><p>Verse 10 </p><p>requite. Suited for that Dispensation. See App-63. </p><p>Verse 11 </p><p>favourest = delightest, or hast pleasure in. Compare Matthew 3:17; Matthew 12:18; Matthew 17:5. Isaiah 42:1. </p><p>triumph = shout with triumph. </p><p>Verse 12 </p><p>Thy face. See note on Exodus 34:20. </p><p>Verse 13 </p><p>Blessed, &amp;c. Hebrew. barak, not &quot;ashrei, as in Psalms 41:1 and the Beatitudes (App-63). This Doxology concludes the first book of Psalms, also the second book (Psalms 72:18-20). They were the words of David when he brought up the Ark (1 Chronicles 16:36), also in 1 Kings 1:47, 1 Kings 1:48, when this group (37-41) was written; also in 1 Chronicles 29:10. They are taken up again in Luke 1:68-70. </p><p>to everlasting: i.e. to the age to come. </p><p>Amen = Truth. Figure of speech Epizeuxis (App-6), for solemn emphasis. </p><p>To the chief Musician. See App-64. </p>"}]}
