{"source":{"id":"thomas_constable_notes","name":"Thomas Constable","worlddicCode":"Dr_Thomas"},"book":"job","chapter":35,"entries":[{"ref":"Job 35","book":"job","chapter":35,"sourceUrl":"https://worlddic.com/xe/sermon4/Dr_Thomas_job_35.html","text":"<p>Verses 1-3 </p><p>Job&quot;s position of indifference35:1-3</p><p>Job had said that living a righteous life does not benefit a person since God does not consistently bless the righteous and punish the wicked in this life ( Job 9:30-31; cf. Job 34:9; Job 35:3). Elihu thought this assertion was hardly a sign of Job&quot;s innocence. In Job 35:2 &quot;more than God&quot;s&quot; is clearer if we read &quot;before God.&quot; &quot;You&quot; in Job 35:3 probably refers to any person (impersonal &quot;you&quot;) rather than God.</p><p>Verses 1-16 </p><p>4. Elihu&quot;s third speech ch35</p><p>We could chart the differences in Elihu&quot;s first three speeches this way.</p><p>Elihu&quot;s Speech</p><p>Job&quot;s question that Elihu answered</p><p>Job&quot;s charge that Elihu refuted</p><p>First</p><p>Why doesn&quot;t God respond to me?</p><p>God is insensitive (ch33).</p><p>Second</p><p>Why doesn&quot;t God relieve me?</p><p>God is unjust (ch34).</p><p>Third</p><p>Why doesn&quot;t God reward me?</p><p>Holiness is unprofitable (ch35).</p><p>Job felt that God should have rewarded him for his innocence, rather than subjecting him to suffering. Elihu replied that man&quot;s sin or innocence does not affect God, and God was silent to Job because Job was proud. As before, Elihu first quoted Job ( Job 35:1-3) and then refuted his statement ( Job 35:4-16).</p><p>Verses 4-16 </p><p>Elihu&quot;s defense of God&quot;s freedom35:4-16</p><p>Elihu made two responses to what he inferred was Job&quot;s attitude. First, he claimed that God is under no obligation to react to people&quot;s actions be they good or bad. He is free to respond or not respond as He chooses. God is above the human sphere of life and only reacts to people when He chooses to do so. This is a thought Eliphaz had expressed earlier ( Job 22:2-3; Job 22:12). However, Elihu went further by pointing out that people&quot;s actions do affect other people ( Job 35:4-8). Therefore, there is an advantage to being holy.</p><p>&quot;There is no place in Elihu&quot;s theology for doing God&quot;s will out of love for him. Man affects only his fellow man by being good or bad ( Job 35:9). And though God may punish or reward man as Judges, there is no place for him in the role of a Father who can be hurt or pleased by man.&quot; [Note: Smick, &quot; Job,&quot; p1016.] </p><p>Second, Elihu spoke to the fact that God does not always provide relief when the oppressed pray to Him ( Job 35:9-16; cf. Job 24:12; Job 36:13). He said often these prayers for help spring from a selfish, proud motive rather than from a sincere desire to learn the reason for one&quot;s sufferings. In this respect humans are like animals; we do not ask for this knowledge. Since God may not answer selfish prayers, it is understandable that He was silent in response to Job&quot;s arrogant, impatient petitions. Elihu counseled Job to wait for God to answer rather than becoming frantic.</p><p>&quot;Job would get his just deserts in due time.&quot; [Note: Habel, p189.] </p><p>&quot;It is always possible to think of a reason for unanswered prayer. The trite explanation, which we hear all too often, is that &quot;You didn&quot;t have enough faith&quot;, or &quot;You prayed from the wrong motive&quot;, or &quot;You must have some hidden, unconfessed sin&quot;. This diagnosis is always applicable. Everyone who prays is aware of the weakness of his faith; everyone with a scrap of self-knowledge knows that his motives are always mixed; everyone who searches his conscience can find no end of fresh sins to be dealt with. If no prayers could be offered and none answered, until all these conditions were satisfied, none would ever be offered and none answered. The Elihus of this world do not care about the cruelty of their perfectionist advice and its unreality. Their theory is saved; that is what matters.&quot; [Note: Andersen, p257.] </p>"}]}
