{"source":{"id":"thomas_constable_notes","name":"Thomas Constable","worlddicCode":"Dr_Thomas"},"book":"genesis","chapter":4,"entries":[{"ref":"Genesis 4","book":"genesis","chapter":4,"sourceUrl":"https://worlddic.com/xe/sermon4/Dr_Thomas_genesis_4.html","text":"<p>Verses 1-8 </p><p>Was Eve thanking God for helping her bear a son (Cain), [Note: Mathews, p265; Wenham, pp101-2.] or was she boasting that she had created a man (Cain) as God had created a man (Adam, Genesis 4:1)? [Note: Sailhamer, The Pentateuch . . ., pp111-12; Waltke, Genesis, p96.] The former alternative seems preferable (cf. Genesis 4:25). &quot;Cain&quot; means &quot;acquisition,&quot; a portent of his own primary proclivity. Abel, from the Hebrew hebel, means &quot;breath, vapor, exhalation, or what ascends.&quot; As things turned out, his life was short, like a vapor. &quot;Abel&quot; also means &quot;meadow&quot; elsewhere.</p><p>Why did God &quot;have regard&quot; for Abel&quot;s offering and not Cain&quot;s ( Genesis 4:4)? It was because Abel had faith ( Hebrews 11:4). What did Abel believe that Cain did not? The Bible does not say specifically. The answer may lie in one or more of the following explanations. [Note: See Jack P. Lewis, &quot;The Offering of Abel ( Genesis 4:4): A History of Interpretation,&quot; Journal of the Evangelical Theological Society37:4 (December1994):481-96.] </p><p>1. Some commentators believed Abel&quot;s attitude reveals his faith. Cain&quot;s improper attitude toward God is evident in Genesis 4:5. [Note: Davis, p99; Pentecost, p41; et al.] </p><p>2. Others say Abel&quot;s faith is evident in his bringing the best of the flock ( Genesis 4:4) whereas Moses did not so describe Cain&quot;s offering ( Genesis 4:3).</p><p>&quot;He [the writer] characterizes Abel&quot;s offerings from the flocks as &quot;from the firstborn&quot; and &quot;from their fat.&quot; By offering the firstborn Abel signified that he recognized God as the Author and Owner of Life. In common with the rest of the ancient Near East, the Hebrews believed that the deity, or lord of the manor, was entitled to the first share of all produce. The firstfruits of plants and the firstborn of animals and man were his....</p><p>&quot;Abel&quot;s offering conformed with this theology; Cain&quot;s did not. In such a laconic story the interpreter may not ignore that whereas Abel&quot;s gift is qualified by &quot;firstborn,&quot; the parallel &quot;firstfruits&quot; does not modify Cain&quot;s....</p><p>&quot;Abel also offered the &quot;fat&quot; which in the Song of Solomon -called &quot;P&quot; [Priestly] material belonged to the Lord and was burned symbolically by the priests. This tastiest and best burning part of the offering represented the best. Abel&quot;s sacrifice, the interlocutor aims to say, passed the test with flying colors. Cain&quot;s sacrifice, however, lacks a parallel to &quot;fat.&quot;&quot; [Note: Bruce K. Waltke, &quot;Cain and His Offering,&quot; Westminster Theological Journal48:2 (Fall1986):368. Cf. idem, Genesis, p97; Keil and Delitzsch, 1:110; and Hamilton, p223.] </p><p>Possibly Cain&quot;s bad attitude resulted in his not offering the best to God. In other words, both options1,2could be correct.</p><p>&quot;Abel went out of his way to please God (which meant he had faith in God, Hebrews 1:6), whereas Cain was simply discharging a duty.&quot; [Note: Ross, &quot; Genesis,&quot; p34.] </p><p>&quot;We think the absence of &quot;firstfruits&quot; for Cain in juxtaposition with Seth&quot;s &quot;firstborn&quot; would not have been lost on the Mosaic audience.</p><p>&quot;Both giver and gift were under the scrutiny of God. Cain&quot;s offering did not measure up because he retained the best of his produce for himself.&quot; [Note: Mathews, p268. I prefer this view.] </p><p>3. Many believe that Abel realized the need for the death of a living substitute to atone for his sins, but Cain did not. If he understood this, he may have learned it by divine revelation that Scripture did not record explicitly. [Note: Thomas, et al.] Perhaps Cain and Abel learned that an animal sacrifice satisfied God whereas a vegetable sacrifice did not from the fact that the fig leaves that Adam and Eve used to cover their nakedness were not satisfactory but an animal skin was ( Genesis 3:7; Genesis 3:21). They provided the fig leaves, but God provided the animal skins. Thus the contrast in the case of Cain and Abel may also be between what man provides (works) and what God provides (grace).</p><p>&quot;Faith always presupposes a Divine revelation to which it is the response ...&quot; [Note: Ibid, p55.] </p><p>&quot;Whatever the cause of God&quot;s rejection of Cain&quot;s offering, the narrative itself focuses our attention on Cain&quot;s response. It is there that the narrative seeks to make its point.&quot; [Note: Sailhamer, The Pentateuch . . ., p112.] </p><p>God questioned Cain, as He had Adam and Eve (cf. Genesis 3:9; Genesis 3:11), to elicit Cain&quot;s admission of sin with a view to repentance, not simply to scold him. His father reluctantly admitted his guilt, but Cain tried to cover it up by lying. Cain was &quot;much more hardened than the first human pair.&quot; [Note: von Rad, p106.] &quot;Sin is crouching at the door&quot; (v7) probably means that the power and tragic consequences of sin could master the person who opens the door to it (cf. Genesis 3:16).</p><p>&quot;The consequences of his reaction to God&quot;s correction are more far-reaching than the initial sin itself, for if he pursues sin&quot;s anger, it will result in sin&quot;s mastery over him. This is his decision. It is possible for Cain to recover from sin quickly if he chooses the right thing.&quot; [Note: Mathews, p270.] </p><p>The Apostle John revealed the reason Cain killed Abel in 1 John 3:12 : &quot;... his own works were evil and his brother&quot;s righteous.&quot; Abel&quot;s attitude of faith in God resulted in righteous works that produced guilt in Cain. The seriousness of Cain&quot;s sin is clear from God&quot;s repeated references to Abel as Cain&quot;s &quot;brother&quot; ( Genesis 4:9-11).</p><p>&quot;If you want to find out Cain&quot;s condition of heart you will find it after the service which he pretended to render; you know a man best out of church ...&quot; [Note: Joseph Parker, The People&quot;s Bible, 1:147.] </p><p>Later, under the Mosaic Law, the fact that a killing took place in a field, out of the range of help, was proof of premeditation (cf. Deuteronomy 22:25-27).</p><p>&quot;Cain and his unrighteous offspring served as a reminder to Israel that its destiny was measured in the scales of ethical behavior.&quot; [Note: Mathews, p269.] </p><p>Verses 1-16 </p><p>2. The murder of Abel4:1-16</p><p>Chapter4shows the spread of sin from Adam&quot;s family to the larger society that his descendants produced. Not only did sin affect everyone, but people became increasingly more wicked as time passed. Human self-assertion leads to violence. Genesis 4:1-16 show that the Fall affected Adam and Eve&quot;s children as well as themselves. Genesis 4:17-26 trace what became of Cain and Seth and their descendants. Note that the chapter begins and ends with the subject of worship.</p><p>God had warned Adam and Eve about sin. Even Song of Solomon, Cain murdered his brother, the beginning of sibling rivalry, because God accepted Abel&quot;s offering but not his own. Sibling rivalry plagued each of the godly families in Genesis. Cain denied responsibility for his sin and objected to the severity of God&quot;s punishment. God graciously provided protection for Cain in response to his complaint. Chapter3gives the cause and chapter4the effect.</p><p>There are structural and conceptual parallels between this pericope (section of verses) and the previous one ( Genesis 2:4 to Genesis 3:24). [Note: Wenham, p99.] </p><p>A Scene1 (narrative): Cain and Abel are active, Yahweh passive ( Genesis 4:2-5).</p><p>B Scene2 (dialogue): Yahweh questions Cain ( Genesis 4:6-7).</p><p>C Scene3 (dialogue and narrative): Cain and Abel are alone ( Genesis 4:8).</p><p>B&quot; Scene4 (dialogue): Yahweh confronts Cain ( Genesis 4:9-14).</p><p>A&quot; Scene5 (narrative): Yahweh is active, Cain passive ( Genesis 4:15-16).</p><p>Both stories conclude with the sinners leaving God&quot;s presence and going to live east of Eden ( Genesis 3:24; Genesis 4:16).</p><p>&quot;. . . though the writer of Genesis wants to highlight the parallels between the two stories, he does not regard the murder of Abel simply as a rerun of the fall. There is development: sin is more firmly entrenched and humanity is further alienated from God.&quot; [Note: Ibid, p100.] </p><p>Verses 9-16 </p><p>As in chapter3, God came investigating the crime with questions ( Genesis 4:9-10). [Note: See P. A. Riemann, &quot;Am I My Brother&quot;s Keeper?&quot; Interpretation24 (1970):482-91.] There the result was God cursing the ground and people generally, but here the result is His cursing Cain, another evidence that wickedness was worsening.</p><p>Cain&quot;s punishment consisted of his being banished from God&quot;s presence and unable to enjoy his family&quot;s company and the fruitfulness of a settled pastoral life ( Genesis 4:11-12; Genesis 4:14). He would have to wander from place to place seeking food rather than living a sedentary life. This punishment was just since he had alienated himself from his brother and God.</p><p>&quot;Cain is not being condemned to a Bedouin-like existence; the terminology is too extreme to describe such a life-style. Rather it seems likely that the curse on Cain reflects the expulsion from the family that was the fate in tribal societies of those who murdered close relatives.... &quot;To be driven away from the land&quot; (cf. Genesis 4:14) is to have all relationships, particularly with the family, broken. Moreover, it is to have one&quot;s relationship with the LORD broken ...&quot; [Note: Wenham, p108.] </p><p>&quot;Nomadism according to the Sumerian flood story is a plight from which the gods rescued man; according to the Bible a nomadic existence was a judgment imposed on the first murderer. This contrast fits in with the overall optimism of Mesopotamia which believes in human progress over against the biblical picture of the inexorable advance of sin ... It would seem likely that the other human achievements listed here-farming, metalwork, and music-are also seen by Genesis as somehow under the shadow of Cain&quot;s sin.&quot; [Note: Ibid, pp98-99.] </p><p>Cain&quot;s response to his punishment was self-pity rather than repentance and an expression of remorse over the extent of his iniquity. [Note: See Waltke, Genesis, p98; Sailhamer, The Pentateuch . . ., p114.] No one would be his keeper (cf. Genesis 4:9).</p><p>Cain&quot;s sin resulted in his being &quot;driven&quot; out ( Genesis 4:14; cf. Genesis 3:23). Note again that sin results in broken relationships and alienation, and alienation from God leads to fear of other people (cf. Job 15:20-25). God in grace allowed Cain and his family to continue to live under His care, but apparently without salvation. Note also that human immorality again impacted earth&quot;s ecology (cf. Genesis 3:17).</p><p>The commentators have interpreted Cain&quot;s &quot;sign&quot; or &quot;mark&quot; ( Genesis 4:15) in a variety of ways. One view is that it was partial paralysis, based on the meaning of the word used to translate &quot;sign&quot; in the Septuatint. An old Jewish interpretation understood it to be the word &quot;Yahweh,&quot; and another viewed it as a long horn growing out of the middle of Cain&quot;s forehead. Some medieval paintings represent Cain with a horn on his head following this view. Other ideas are that it was some other identifying mark on Cain in view of parallels with other marks that identify and protect their bearers in Scripture (cf. Ezekiel 9:4; Revelation 7:3; Revelation 13:16-18; Revelation 14:1). [Note: Mathews, p278; Wenham, p109; Waltke, Genesis, p99.] Still other interpreters believe that the mark was a verification of God&quot;s promise to Cain. This last view rests on the usual meaning of &quot;sign&quot; in the Old Testament (cf. Judges 6:36-40; 2 Kings 2:9-12; et al.), which the Hebrew construction supports here. [Note: See Bush, p104.] The text does not identify the sign, but it was some immediate indication that God gave Cain to assure him that he would not die (cf. Genesis 21:13; Genesis 21:18; Genesis 27:37; Genesis 45:7; Genesis 45:9; Genesis 46:3 with Genesis 21:14; Genesis 44:21). Whatever it was, Cain&quot;s mark served to protect him as well as to remind him and others of his banishment.</p><p>&quot;Nod&quot; ( Genesis 4:16) means &quot;wandering,&quot; so the very name of the place where he lived also reminded Cain of his sentence ( Genesis 4:12).</p><p>&quot;The ungodly here are portrayed as living on in the world (with a protective mark of grace ...) without being saved. Their sense of guilt was eased by their cultural development and their geographical expansion.&quot; [Note: Ross, &quot; Genesis,&quot; p33.] </p><p>Cain was a man who did not care to please God. Because he did not, God did not bless him as He did Abel, who was a man of faith. Cain&quot;s anger and jealousy over Abel&quot;s blessing brought disaster on himself. God has preserved his example to help us avoid it. Those who worship God must have as their goal to please Him rather than letting envy and hatred ruin their lives.</p><p>Verses 17-24 </p><p>The descendants of Cain4:17-24</p><p>&quot;By virtue of being Cain&quot;s descendants, the people named in the genealogy all inherit his curse. Thus the Cainite genealogy becomes part of the Yahwist&quot;s account of man&quot;s increasing sin.&quot; [Note: R. R. Wilson, Genealogy and History in the Biblical World, p155.] </p><p>Cain&quot;s wife ( Genesis 4:17) was evidently one of his sisters or nieces (cf. Genesis 5:4). God did not prohibit marrying siblings and close relatives until the Mosaic Law.</p><p>&quot;Because harmful mutations so greatly outnumber any supposed helpful ones, it&quot;s considered unwise nowadays (and illegal in many states) to marry someone too closely related to you. Why? Because you greatly increase the odds that bad genes will show up. By the way, you also increase the odds of bringing out really excellent trait combinations. But did you ever hear anybody say, &quot;Don&quot;t marry your first cousin or you&quot;ll have a genius for a child?&quot; They don&quot;t usually say that, because the odds of something bad happening are far, far, far, far, far greater.</p><p>&quot;That would not have been a problem, by the way, shortly after creation (no problem for Cain and his wife, for example). Until mutations had a chance to accumulate in the human population, no such risk of bad combinations existed.&quot; [Note: Gary Parker, Creation Facts of Life, p98. This is an excellent book that deals with the evidence of creation, Darwin and biologic change, and the fossil evidence. See also Ham, et al, pp17, 177-85.] </p><p>Lamech ( Genesis 4:19) was the first bigamist. Bigamy was common in the ancient Near East, but it was never God&quot;s desire (cf. Genesis 2:24; Matthew 19:4-5). God permitted it, however, as He did many other customs of which He disapproved (e.g, divorce, marrying concubines, polygamy, etc.). That Isaiah, He allowed people who practiced them to continue to live.</p><p>&quot;To be sure, no rebuke from God is directed at Lamech for his violation of the marital arrangement. It is simply recorded. But that is the case with most OT illustrations of polygamy. Abraham is not condemned for cohabiting with Sarah and Hagar, nor is Jacob for marrying simultaneously Leah and Rachel. In fact, however, nearly every polygamous househould [sic] in the OT suffers most unpleasant and shattering experiences precisely because of this ad hoc relationship. The domestic struggles that ensue are devastating.&quot; [Note: Hamilton, p238. Cf. Deuteronomy 21:15-17.] </p><p>&quot;Cain&quot;s family is a microcosm: its pattern of technical prowess and moral failure is that of humanity.&quot; [Note: Kidner, p78.] </p><p>God shows the destructive consequences of sin (cf. Genesis 2:24) more often than He states them in the Old Testament. Polygamy is one form of sin.</p><p>Polygamy is &quot;. . . the symptom of an unbalanced view of marriage, which regards it as an institution in which the wife&quot;s ultimate raison d&quot;etre [reason for being] is the production of children. Where God had created the woman first and foremost for partnership, society made her in effect a means to an end, even if a noble end, and wrote its view into its marriage contracts.&quot; [Note: Ibid, p36.] </p><p>This is the first occurrence of polygamy in Genesis. We shall find several cases of it throughout the Old Testament. People practiced it widely in the ancient Near East, but it was contrary to the will of God ( Genesis 2:24). Besides indulging the flesh, polygamy was an attempt to ensure the survival of the family by providing male successors. [Note: For a good, brief introduction to polygamy, see M. Stephen Davis, &quot;Polygamy in the Ancient World,&quot; Biblical Illustrator14:1 (Fall1987):34-36.] The presence of polygamy in Lamech&quot;s generation shows how sin escalated in the marriage relationship following the Fall.</p><p>The reference to forging (lit. sharpening) iron implements ( Genesis 4:22) appears anacronistic since the smelting of iron was not common until the Iron Age, in the second millennium B.C. Perhaps this is a reference to the cold forging of meteoric iron, which was common earlier. [Note: The New Bible Dictionary, 1962ed, s.v. &quot;Mining and Metals,&quot; by A. Stuart. See also Mathews, p287; and Hamilton, p239.] </p><p>We could paraphrase the idea in Lamech&quot;s mind as expressed in Genesis 4:23-24 more clearly as follows. &quot;If I am threatened again, I will retaliate again, even more forcefully than Cain did.&quot; Lamech may have been claiming that he had killed in self-defense. Nevertheless he was boasting and shows himself thereby to be more barbaric than his forefather Cain (cf. Exodus 21:25). The seventh generations from Adam through Cain and Seth, ungodly Lamech ( Genesis 4:19-24) and godly Enoch ( Genesis 5:24), stand in sharp contrast to each other. The former man inflicts death, and the latter does not die. Some scholars have called Lamech&quot;s poem the &quot;Song of the Sword.&quot; Lamech thought himself invincible with his newly acquired weapons.</p><p>&quot;Both Cain&quot;s antediluvian lineage and the postdiluvian Babel cautioned later Israel that cities founded upon arrogance resulted in violence and ultimately destruction.&quot; [Note: Mathews, pp282-83.] </p><p>Verses 17-26 </p><p>3. The spread of civilization and sin4:17-26</p><p>Cain prospered even though he rebelled against God. This is another indication of God&quot;s grace. Cain&quot;s descendants took the lead in building cities, developing music, advancing agriculture, creating weapons, and spreading civilization. However the descendants of Seth made an even more important advance, the worship of God.</p><p>Verse 25-26 </p><p>The family of Seth4:25-26</p><p>Seth&quot;s name, from the Hebrew verb translated &quot;granted&quot; and meaning &quot;to set or place,&quot; expresses Eve&quot;s faith that God would continue to provide seed despite death. [Note: Waltke, Genesis, p101.] </p><p>Many commentators regarded Genesis 4:26 as the first reference to prayer as we know it in the Bible. Prayer is basic to man&quot;s relationship with God, which is a major theme in Genesis. However the phrase &quot;call on the name of the Lord&quot; usually refers to proclamation rather than prayer in the Pentateuch. [Note: Ross, Creation and . . ., p169.] Here it probably refers to the beginning of public worship of Yahweh.</p><p>&quot; Genesis 4concludes the story of mankind that was cut off in the flood, a tale that opened with Genesis 2:4, &quot;This is the history....&quot; With the aid of a genealogy from Adam to Lamek, the seventh generation, it traces the development of technology and arts on the one hand and the growth of violence on the other. Only in the last two verses introducing the descendants of Seth do we have glimmers of hope, for from him, as chap5 will describe, descended Noah, the survivor of the flood, and it was in Enosh&quot;s day that the public worship of God was reintroduced.&quot; [Note: Wenham, p116.] </p><p>Chapter4also teaches that it is important for the righteous to preserve the knowledge of God when they live in an ungodly society.</p>"}]}
